fcmaesray/__init__.py
fcmaesray/multiretry.py
fcmaesray/rayretry.py
fcmaesray-0.1.3.dist-info/LICENSE
fcmaesray-0.1.3.dist-info/METADATA
fcmaesray-0.1.3.dist-info/WHEEL
fcmaesray-0.1.3.dist-info/top_level.txt
fcmaesray-0.1.3.dist-info/RECORD
